Workbook

Sheet Assumptions & Levers
A1: FWA 5G n50 (60 MHz) — DICT / UNDP GIDA Financial Model (Revision 2 Audited)
A2: Source of Truth: Siting demographics & audited fiber transmission screening. Author: OLIVER TUNGOL
A4: Category | B4: Assumption / Parameter | C4: Default Value | D4: Unit | E4: Source Reference / Engineering Rationale
A5: Global Financials | B5: Exchange Rate (PHP/USD) | C5: 55 | D5: PHP/USD | E5: Baseline FX rate (test 55 to 65)
A6: Global Financials | B6: Discount Rate / WACC | C6: 0.12 | D6: % | E6: Nominal Weighted Average Cost of Capital
A7: Global Financials | B7: Corporate Income Tax Rate | C7: 0.25 | D7: % | E7: Philippine CREATE Act corporate tax rate
A8: Global Financials | B8: Annual Cost Inflation | C8: 0.05 | D8: % p.a. | E8: Annual escalation for ongoing OPEX
A9: Global Financials | B9: Modeling Horizon | C9: 10 | D9: years | E9: 10-year full deployment lifecycle
A10: Deployment & Scale | B10: Day-1 Sites Deployed (Year 1) | C10: 1000 | D10: sites | E10: Phase 1 priority rollout footprint
A11: Deployment & Scale | B11: Sites Added per Year (Y2-Y5) | C11: 1000 | D11: sites/yr | E11: Phased deployment scaling to 5,000 sites
A12: Deployment & Scale | B12: Total Program Footprint | C12: 5000 | D12: sites | E12: Total nationwide barangay footprint
A13: Deployment & Scale | B13: Total Addressable Subscribers (30%) | C13: 1357667 | D13: subs | E13: Sum of target households @ 30% take-rate across DICT / UNDP GIDA
A14: Deployment & Scale | B14: Peak Expansion BTS Required | C14: 5554 | D14: BTS | E14: @ 1,000 subs / 3-sector 8T8R BTS capacity limit
A15: Transmission Mix (P1) | B15: Phase 1 Direct Node Drops (Class A/B) | C15: 189 | D15: sites | E15: Audited short node connections <=1 km (18.9%)
A16: Transmission Mix (P1) | B16: Phase 1 Splice Line-Taps (Class C) | C16: 89 | D16: sites | E16: Audited line taps <=500m (8.9%)
... A38: Tower Infrastructure | B38: Own-Site Ground Land Lease OPEX | C38: 25000 | D38: PHP/site/mo | E38: Land rental for own-built greenfield monopole sites

Sheet 10-Year Cash Flow & Scenarios
A1: 10-Year Financial Feasibility & Scenario Analysis — DICT / UNDP GIDA
A2: Audited 4-Tier Transmission Mix | 8T8R Sizing | Leased Towers vs Own Build
A4: Metric / Cash Flow Line ($M USD) | B4: Category | C4: 10-Yr Total | D4: Year 1 | E4: Year 2 | F4: Year 3 | G4: Year 4 | H4: Year 5 | I4: Year 6 | J4: Year 7 | K4: Year 8 | L4: Year 9 | M4: Year 10
A5: Network Cumulative Sites | B5: Scale | C5: =SUM(D5:M5) | D5: ='Assumptions & Levers'!$C$10 | E5: =D5+'Assumptions & Levers'!$C$11 | F5: =E5+'Assumptions & Levers'!$C$11 | G5: =F5+'Assumptions & Levers'!$C$11 | H5: =G5+'Assumptions & Levers'!$C$11 | I5: =H5 | J5: =I5 | K5: =J5 | L5: =K5 | M5: =L5
A6: Active Subscribers | B6: Scale | C6: =SUM(D6:M6) | D6: 120000 | E6: 300000 | F6: 550000 | G6: 850000 | H6: 1100000 | I6: 1200000 | J6: 1260000 | K6: 1300000 | L6: 1330000 | M6: 1358095
A7: Gross Subscription Revenue ($M) | B7: Revenue | C7: =SUM(D7:M7) | D7: =ROUND(D6*('Assumptions & Levers'!$C$20/'Assumptions & Levers'!$C$5)*12/1000000, 2) | E7: =ROUND(E6*('Assumptions & Levers'!$C$20/'Assumptions & Levers'!$C$5)*12/1000000, 2) | F7: =ROUND(F6*('Assumptions & Levers'!$C$20/'Assumptions & Levers'!$C$5)*12/1000000, 2) | G7: =ROUND(G6*('Assumptions & Levers'!$C$20/'Assumptions & Levers'!$C$5)*12/1000000, 2) | H7: =ROUND(H6*('Assumptions & Levers'!$C$20/'Assumptions & Levers'!$C$5)*12/1000000, 2) | I7: =ROUND(I6*('Assumptions & Levers'!$C$20/'Assumptions & Levers'!$C$5)*12/1000000, 2) | J7: =ROUND(J6*('Assumptions & Levers'!$C$20/'Assumptions & Levers'!$C$5)*12/1000000, 2) | K7: =ROUND(K6*('Assumptions & Levers'!$C$20/'Assumptions & Levers'!$C$5)*12/1000000, 2) | ... M7: =ROUND(M6*('Assumptions & Levers'!$C$20/'Assumptions & Levers'!$C$5)*12/1000000, 2)
A8: TowerCo Lease OPEX ($M) | B8: OPEX | C8: =SUM(D8:M8) | D8: =ROUND((D5*'Assumptions & Levers'!$C$34*'Assumptions & Levers'!$C$36*12+D5*'Assumptions & Levers'!$C$35*'Assumptions & Levers'!$C$38*12)/('Assumptions & Levers'!$C$5*1000000), 2) | E8: =ROUND((E5*'Assumptions & Levers'!$C$34*'Assumptions & Levers'!$C$36*12+E5*'Assumptions & Levers'!$C$35*'Assumptions & Levers'!$C$38*12)/('Assumptions & Levers'!$C$5*1000000), 2) | F8: =ROUND((F5*'Assumptions & Levers'!$C$34*'Assumptions & Levers'!$C$36*12+F5*'Assumptions & Levers'!$C$35*'Assumptions & Levers'!$C$38*12)/('Assumptions & Levers'!$C$5*1000000), 2) | G8: =ROUND((G5*'Assumptions & Levers'!$C$34*'Assumptions & Levers'!$C$36*12+G5*'Assumptions & Levers'!$C$35*'Assumptions & Levers'!$C$38*12)/('Assumptions & Levers'!$C$5*1000000), 2) | H8: =ROUND((H5*'Assumptions & Levers'!$C$34*'Assumptions & Levers'!$C$36*12+H5*'Assumptions & Levers'!$C$35*'Assumptions & Levers'!$C$38*12)/('Assumptions & Levers'!$C$5*1000000), 2) | I8: =ROUND((I5*'Assumptions & Levers'!$C$34*'Assumptions & Levers'!$C$36*12+I5*'Assumptions & Levers'!$C$35*'Assumptions & Levers'!$C$38*12)/('Assumptions & Levers'!$C$5*1000000), 2) | J8: =ROUND((J5*'Assumptions & Levers'!$C$34*'Assumptions & Levers'!$C$36*12+J5*'Assumptions & Levers'!$C$35*'Assumptions & Levers'!$C$38*12)/('Assumptions & Levers'!$C$5*1000000), 2) | K8: =ROUND((K5*'Assumptions & Levers'!$C$34*'Assumptions & Levers'!$C$36*12+K5*'Assumptions & Levers'!$C$35*'Assumptions & Levers'!$C$38*12)/('Assumptions & Levers'!$C$5*1000000), 2) | ... M8: =ROUND((M5*'Assumptions & Levers'!$C$34*'Assumptions & Levers'!$C$36*12+M5*'Assumptions & Levers'!$C$35*'Assumptions & Levers'!$C$38*12)/('Assumptions & Levers'!$C$5*1000000), 2)
A9: Audited Backhaul OPEX ($M) | B9: OPEX | C9: =SUM(D9:M9) | D9: =ROUND((D5*0.5646*46000*12+D5*0.4354*'Assumptions & Levers'!$C$31*12)/('Assumptions & Levers'!$C$5*1000000), 2) | E9: =ROUND((E5*0.5646*46000*12+E5*0.4354*'Assumptions & Levers'!$C$31*12)/('Assumptions & Levers'!$C$5*1000000), 2) | F9: =ROUND((F5*0.5646*46000*12+F5*0.4354*'Assumptions & Levers'!$C$31*12)/('Assumptions & Levers'!$C$5*1000000), 2) | G9: =ROUND((G5*0.5646*46000*12+G5*0.4354*'Assumptions & Levers'!$C$31*12)/('Assumptions & Levers'!$C$5*1000000), 2) | H9: =ROUND((H5*0.5646*46000*12+H5*0.4354*'Assumptions & Levers'!$C$31*12)/('Assumptions & Levers'!$C$5*1000000), 2) | I9: =ROUND((I5*0.5646*46000*12+I5*0.4354*'Assumptions & Levers'!$C$31*12)/('Assumptions & Levers'!$C$5*1000000), 2) | J9: =ROUND((J5*0.5646*46000*12+J5*0.4354*'Assumptions & Levers'!$C$31*12)/('Assumptions & Levers'!$C$5*1000000), 2) | K9: =ROUND((K5*0.5646*46000*12+K5*0.4354*'Assumptions & Levers'!$C$31*12)/('Assumptions & Levers'!$C$5*1000000), 2) | ... M9: =ROUND((M5*0.5646*46000*12+M5*0.4354*'Assumptions & Levers'!$C$31*12)/('Assumptions & Levers'!$C$5*1000000), 2)
A10: Network Active Telecom O&M ($M) | B10: OPEX | C10: =SUM(D10:M10) | D10: =ROUND(D5*(120000/'Assumptions & Levers'!$C$5)*12/1000000, 2) | E10: =ROUND(E5*(120000/'Assumptions & Levers'!$C$5)*12/1000000, 2) | F10: =ROUND(F5*(120000/'Assumptions & Levers'!$C$5)*12/1000000, 2) | G10: =ROUND(G5*(120000/'Assumptions & Levers'!$C$5)*12/1000000, 2) | H10: =ROUND(H5*(120000/'Assumptions & Levers'!$C$5)*12/1000000, 2) | I10: =ROUND(I5*(120000/'Assumptions & Levers'!$C$5)*12/1000000, 2) | J10: =ROUND(J5*(120000/'Assumptions & Levers'!$C$5)*12/1000000, 2) | K10: =ROUND(K5*(120000/'Assumptions & Levers'!$C$5)*12/1000000, 2) | ... M10: =ROUND(M5*(120000/'Assumptions & Levers'!$C$5)*12/1000000, 2)
A11: Total Operating Expenses ($M) | B11: OPEX | C11: =SUM(D11:M11) | D11: =SUM(D8:D10) | E11: =SUM(E8:E10) | F11: =SUM(F8:F10) | G11: =SUM(G8:G10) | H11: =SUM(H8:H10) | I11: =SUM(I8:I10) | J11: =SUM(J8:J10) | K11: =SUM(K8:K10) | ... M11: =SUM(M8:M10)
A12: EBITDA ($M) | B12: Profitability | C12: =SUM(D12:M12) | D12: =D7-D11 | E12: =E7-E11 | F12: =F7-F11 | G12: =G7-G11 | H12: =H7-H11 | I12: =I7-I11 | J12: =J7-J11 | K12: =K7-K11 | ... M12: =M7-M11
A13: BTS & RAN CAPEX ($M) | B13: CAPEX | C13: =SUM(D13:M13) | D13: =ROUND('Assumptions & Levers'!$C$10*('Assumptions & Levers'!$C$21+'Assumptions & Levers'!$C$22)/1000000, 2) | E13: =ROUND('Assumptions & Levers'!$C$11*('Assumptions & Levers'!$C$21+'Assumptions & Levers'!$C$22)/1000000, 2) | F13: =ROUND('Assumptions & Levers'!$C$11*('Assumptions & Levers'!$C$21+'Assumptions & Levers'!$C$22)/1000000, 2) | G13: =ROUND('Assumptions & Levers'!$C$11*('Assumptions & Levers'!$C$21+'Assumptions & Levers'!$C$22)/1000000, 2) | H13: =ROUND('Assumptions & Levers'!$C$11*('Assumptions & Levers'!$C$21+'Assumptions & Levers'!$C$22)/1000000, 2) | I13: 0 | J13: 0 | K13: 0 | L13: 0 | M13: 0
A14: Own-Site Monopole Build CAPEX ($M) | B14: CAPEX | C14: =SUM(D14:M14) | D14: =ROUND('Assumptions & Levers'!$C$10*'Assumptions & Levers'!$C$35*'Assumptions & Levers'!$C$37/('Assumptions & Levers'!$C$5*1000000), 2) | E14: =ROUND('Assumptions & Levers'!$C$11*'Assumptions & Levers'!$C$35*'Assumptions & Levers'!$C$37/('Assumptions & Levers'!$C$5*1000000), 2) | F14: =ROUND('Assumptions & Levers'!$C$11*'Assumptions & Levers'!$C$35*'Assumptions & Levers'!$C$37/('Assumptions & Levers'!$C$5*1000000), 2) | G14: =ROUND('Assumptions & Levers'!$C$11*'Assumptions & Levers'!$C$35*'Assumptions & Levers'!$C$37/('Assumptions & Levers'!$C$5*1000000), 2) | H14: =ROUND('Assumptions & Levers'!$C$11*'Assumptions & Levers'!$C$35*'Assumptions & Levers'!$C$37/('Assumptions & Levers'!$C$5*1000000), 2) | I14: 0 | J14: 0 | K14: 0 | L14: 0 | M14: 0
A15: Audited Transmission CAPEX ($M) | B15: CAPEX | C15: =SUM(D15:M15) | D15: =ROUND('Assumptions & Levers'!$C$11*(0.5646*'Assumptions & Levers'!$C$25+0.4354*'Assumptions & Levers'!$C$27)/1000000, 2) | E15: =ROUND('Assumptions & Levers'!$C$11*(0.5646*'Assumptions & Levers'!$C$25+0.4354*'Assumptions & Levers'!$C$27)/1000000, 2) | F15: =ROUND('Assumptions & Levers'!$C$11*(0.5646*'Assumptions & Levers'!$C$25+0.4354*'Assumptions & Levers'!$C$27)/1000000, 2) | G15: =ROUND('Assumptions & Levers'!$C$11*(0.5646*'Assumptions & Levers'!$C$25+0.4354*'Assumptions & Levers'!$C$27)/1000000, 2) | H15: =ROUND('Assumptions & Levers'!$C$11*(0.5646*'Assumptions & Levers'!$C$25+0.4354*'Assumptions & Levers'!$C$27)/1000000, 2) | I15: 0 | J15: 0 | K15: 0 | L15: 0 | M15: 0
A16: CPE Device CAPEX ($M) | B16: CAPEX | C16: =SUM(D16:M16) | D16: =ROUND(D6*'Assumptions & Levers'!$C$23/1000000, 2) | E16: =ROUND((E6-D6)*'Assumptions & Levers'!$C$23/1000000, 2) | F16: =ROUND((F6-E6)*'Assumptions & Levers'!$C$23/1000000, 2) | G16: =ROUND((G6-F6)*'Assumptions & Levers'!$C$23/1000000, 2) | H16: =ROUND((H6-G6)*'Assumptions & Levers'!$C$23/1000000, 2) | I16: =ROUND((I6-H6)*'Assumptions & Levers'!$C$23/1000000, 2) | J16: =ROUND((J6-I6)*'Assumptions & Levers'!$C$23/1000000, 2) | K16: =ROUND((K6-J6)*'Assumptions & Levers'!$C$23/1000000, 2) | L16: =ROUND((L6-K6)*'Assumptions & Levers'!$C$23/1000000, 2) | M16: =ROUND((M6-L6)*'Assumptions & Levers'!$C$23/1000000, 2)
A17: Total Capital Expenditure ($M) | B17: CAPEX | C17: =SUM(D17:M17) | D17: =SUM(D13:D16) | E17: =SUM(E13:E16) | F17: =SUM(F13:F16) | G17: =SUM(G13:G16) | H17: =SUM(H13:H16) | I17: =SUM(I13:I16) | J17: =SUM(J13:J16) | K17: =SUM(K13:K16) | ... M17: =SUM(M13:M16)
A18: Free Cash Flow ($M) | B18: Cash Flow | C18: =SUM(D18:M18) | D18: =D12-D17 | E18: =E12-E17 | F18: =F12-F17 | G18: =G12-G17 | H18: =H12-H17 | I18: =I12-I17 | J18: =J12-J17 | K18: =K12-K17 | ... M18: =M12-M17
A19: Cumulative Free Cash Flow ($M) | B19: Cash Flow | C19: =M18 | D19: =D18 | E19: =D19+E18 | F19: =E19+F18 | G19: =F19+G18 | H19: =G19+H18 | I19: =H19+I18 | J19: =I19+J18 | K19: =J19+K18 | L19: =K19+L18 | M19: =L19+M18
A21: EXECUTIVE VALUATION & RETURN METRICS
A22: Project 10-Yr NPV (@ 12% WACC) | B22: =NPV('Assumptions & Levers'!$C$6, D18:M18) | C22: Discounted cumulative cash return
A23: Unlevered Project IRR (%) | B23: =IRR(D18:M18) | C23: Internal rate of return across 10 years
A24: Simple Payback Period | B24: =IF(M19<0, "No Payback (>10 Yrs)", TEXT(ROUND(COUNTIF(D19:M19, "<0") + ABS(INDEX(D19:M19, 1, COUNTIF(D19:M19, "<0"))) / INDEX(D18:M18, 1, COUNTIF(D19:M19, "<0") + 1), 1), "0.0") & " Years") | C24: Time to recover cumulative initial capital
A25: Peak Capital Funding Required | B25: =ABS(MIN(0, MIN(D19:M19))) | C25: Maximum cumulative cash deficit before self-funding
