Workbook

Sheet Read Me - Data Dictionary
A1: RFP COMMERCIAL PRICE BOOK & BILL OF QUANTITIES — DATA DICTIONARY & READ ME
A2: Project: Nationwide 5G FWA Network (Band n50, 60 MHz TDD) | 5,000 Sites Footprint
A3: Operator: Telecommunications Technology Solutions Incorporated (TelTech) | Author: OLIVER TUNGOL
A4: Tender Ref: RFP-TELTECH-FWA-2026-001 | Version: Official Bidding Version (Blank BoQ) | Date: October 14, 2026
A6: Tab Ref / Sheet Name | B6: Column Header | C6: Data Type | D6: Required / Formula | E6: Operational Definition & Engineering Purpose for Bidders
A7: Tender Summary & Instructions | B7: Instructions & Summary | C7: Text / Matrix | D7: Informational | E7: Overview of bidding currency (USD/PHP), 180-day price validity, scope boundaries, yellow input cell guidelines, and lot descriptions.
A8: Lot 1 - RAN & Rollout | B8: Item Code | C8: Alphanumeric Code | D8: Mandatory Code | E8: Unique reference identifier for RAN hardware and services (e.g. RAN-HW-01 for BBU, RAN-SVC-01 for TSSR).
A9: Lot 1 - RAN & Rollout | B9: Item Description | C9: Text Description | D9: Specification | E9: Commercial name of the access equipment subsystem or turnkey rollout engineering activity.
A10: Lot 1 - RAN & Rollout | B10: Detailed Technical Specification | C10: Text Description | D10: Compliance Basis | E10: Mandatory technical standards (e.g., Band n50, 60 MHz TDD, 8T8R 320W RF power, eCPRI interfaces).
A11: Lot 1 - RAN & Rollout | B11: Qty / Site | C11: Integer | D11: Dimensioning | E11: Standard quantity deployed per macro site (e.g., 1 BBU, 3 RRUs, 3 Antennas per 3-sector macro BTS).
A12: Lot 1 - RAN & Rollout | B12: UoM | C12: Unit of Measure | D12: Standard UoM | E12: Commercial billing unit: set, lot, site, or system.
A13: Lot 1 - RAN & Rollout | B13: Unit Rate (USD) | C13: Currency ($ USD) | D13: BIDDER TO QUOTE | E13: Firm, fixed unit price quoted by Bidder in US Dollars (Yellow input cells).
A14: Lot 1 - RAN & Rollout | B14: Total per Site (USD) | C14: Currency ($ USD) | D14: Formula (=Qty*Rate) | E14: Turnkey total access Capex per individual BTS site.
A15: Lot 1 - RAN & Rollout | B15: Phase 1 Total (1,000 Sites) | C15: Currency ($ USD) | D15: Formula (=Site*1,000) | E15: Aggregate Year-1 Capex commitment for Phase 1 priority rollout (1,000 BTS sites).
A16: Lot 1 - RAN & Rollout | B16: Program Total (5,000 Sites) | C16: Currency ($ USD) | D16: Formula (=Site*5,000) | E16: Full 5-year nationwide network Capex commitment across all 5,000 macro sites.
A17: Lot 1 - RAN & Rollout | B17: Remarks / Bidder Model | C17: Text / Alphanumeric | D17: Bidder Notes | E17: Bidder equipment model numbers, hardware datasheets, and compliance cross-references.
... A83: Form D - Vendor Financing | B83: Compliance / Notes | C83: Text Description | D83: Bidder Notes | E83: Compliance confirmation (Compliant / Minor Deviation / Exception), ECA facility details (e.g. Sinosure, EKN, Finnvera, JBIC), term sheet references, and drawdown conditions.

Sheet Tender Summary & Instructions
A1: REQUEST FOR PROPOSAL (RFP) — COMMERCIAL PRICE BOOK & BILL OF QUANTITIES (BoQ)
A2: Project: Nationwide 5G FWA Network (Band n50, 60 MHz TDD) | 5,000 Sites Footprint
A3: Operator: Telecommunications Technology Solutions Incorporated (TelTech)
A4: Tender Document Reference: RFP-TELTECH-FWA-2026-001 | Version: Official Bidding Version
A6: 1. Instructions to Bidders
A7: Currency of Bidding | B7: All hardware, international software licenses, and CPE devices must be quoted in US Dollars (USD $). Local services, civil works, and managed operations may be quoted in USD or Philippine Pesos (PHP ₱ at baseline FX: 55.00 PHP/USD).
A8: Price Validity | B8: All quoted unit prices, license fees, and service rates must remain firm, fixed, and contractually binding for at least 180 calendar days from the official tender closing date.
A9: Turnkey Scope | B9: Quotes must reflect full turnkey delivery including ocean freight/air freight, customs clearance, import duties, local warehousing, transport hauling to remote barangays, installation, commissioning, and acceptance testing.
A10: Yellow Input Cells | B10: Bidders must enter their firm unit rates and commercial offers directly into the designated highlighted cells. Formulas in Total columns will calculate automatically.
A11: Vendor Financing (Form D) | B11: Completion of Tab "Form D - Vendor Financing" is mandatory. Bidders offering attractive OEM or ECA-backed financing facilities will receive preferential evaluation scoring.
A13: 2. Summary of Tender Lots | B13: Tab Name Reference
A14: Lot 1: 5G RAN Equipment & Turnkey Rollout Services | B14: Lot 1 - RAN & Rollout
A15: Lot 2: Power Systems & Passive Site Infrastructure | B15: Lot 2 - Power & Passive
A16: Lot 3: Cloud-Native 5G Core Network (5GC SA) | B16: Lot 3 - 5G Core
A17: Lot 4: Converged Digital OSS/BSS & Field Dispatch Automation | B17: Lot 4 - OSS-BSS
A18: Lot 5: Site Acquisition, Detailed Site Survey (TSSR), RF Design & Civil Works | B18: Lot 5 - Site Acq & Civils
A19: Lot 6: Managed Services & 24/7 First Line Maintenance | B19: Lot 6 - Managed Services
... A21: Form D: Mandatory Vendor Financing Proposal | B21: Form D - Vendor Financing

Sheet Lot 1 - RAN & Rollout
A1: LOT 1: 5G RADIO ACCESS NETWORK (RAN) HARDWARE & TURNKEY SERVICES
A2: Official Bidding Bill of Quantities — Enter Quoted Unit Rates in Column F
A4: Item Code | B4: Item Description | C4: Detailed Technical Specification | D4: Qty / Site | E4: UoM | F4: Unit Rate (USD) [Bidder Input] | G4: Total per Site (USD) | H4: Phase 1 Total (1,000 Sites) | I4: Program Total (5,000 Sites) | J4: Remarks / Bidder Model
A5: RAN-HW-01 | B5: 5G Baseband Unit (BBU) | C5: Modular 19" subrack, dual -48V DC PSU, 4x25G backhaul, 6x25G eCPRI, PTP/SyncE | D5: 1 | E5: set | G5: =D5*F5 | H5: =G5*1000 | I5: =G5*5000
A6: RAN-HW-02 | B6: 8T8R Remote Radio Unit (RRU) | C6: Band n50 (1.5 GHz), 60 MHz IBW, 8x40W (320W total RF power), IP67, fanless | D6: 3 | E6: sets | G6: =D6*F6 | H6: =G6*1000 | I6: =G6*5000
A7: RAN-HW-03 | B7: Macro 8-Port Antennas | C7: 8-port cross-pol, 17.5 dBi gain, 65 deg beamwidth, internal AISG 2.0 eRET | D7: 3 | E7: sets | G7: =D7*F7 | H7: =G7*1000 | I7: =G7*5000
A8: RAN-HW-04 | B8: RF Jumpers, Fiber Patchcords & SPD | C8: Armored optical jumpers, DC SPD Type 2, grounding kits, waterproof boots | D8: 1 | E8: lot | G8: =D8*F8 | H8: =G8*1000 | I8: =G8*5000
A9: RAN-HW-05 | B9: BBU Base Software & 5G Features | C9: Band n50 carrier license, 60 MHz TDD, 8T8R MU-MIMO, dynamic beamforming, energy-saving | D9: 1 | E9: lot | G9: =D9*F9 | H9: =G9*1000 | I9: =G9*5000
A10: SUBTOTAL-HW | B10: Subtotal BTS Hardware Package | C10: Total BTS Hardware Package per Site | E10: site | G10: =SUM(G5:G9) | H10: =SUM(H5:H9) | I10: =SUM(I5:I9)
A11: RAN-SVC-01 | B11: Site Survey, Structural Audit & TSSR | C11: Tower load audit, drone 360 photo sweep, power check, TSSR report | D11: 1 | E11: site | G11: =D11*F11 | H11: =G11*1000 | I11: =G11*5000
A12: RAN-SVC-02 | B12: Project Management & Mobilization | C12: Dedicated PMO, rollout staging, quality assurance, safety management | D12: 1 | E12: site | G12: =D12*F12 | H12: =G12*1000 | I12: =G12*5000
A13: RAN-SVC-03 | B13: Installation, Testing & Commissioning (I&C) | C13: Rigging, antenna/RRU mount, BBU wiring, fiber termination, power-up | D13: 1 | E13: site | G13: =D13*F13 | H13: =G13*1000 | I13: =G13*5000
A14: RAN-SVC-04 | B14: Single Site Optimization (SSO/SSV) | C14: Stationary throughput, sector call test, ping, eRET tuning, SSV report | D14: 1 | E14: site | G14: =D14*F14 | H14: =G14*1000 | I14: =G14*5000
A15: RAN-SVC-05 | B15: Cluster RF Optimization Services | C15: Cluster drive test, pilot pollution removal, neighbor tuning (per site share) | D15: 1 | E15: site | G15: =D15*F15 | H15: =G15*1000 | I15: =G15*5000
A16: RAN-SVC-06 | B16: Central Warehousing & Logistics | C16: Staging, serial asset tagging, indoor climate storage, kitting | D16: 1 | E16: site | G16: =D16*F16 | H16: =G16*1000 | I16: =G16*5000
A17: RAN-SVC-07 | B17: Delivery & Basic Hauling to Site | C17: Transport to regional depots, 4x4 rough-road hauling to rural barangays | D17: 1 | E17: site | G17: =D17*F17 | H17: =G17*1000 | I17: =G17*5000
A18: SUBTOTAL-SVC | B18: Subtotal Turnkey Services | C18: Total RAN Turnkey Rollout Services per Site | E18: site | G18: =SUM(G11:G17) | H18: =SUM(H11:H17) | I18: =SUM(I11:I17)
A19: TOTAL-LOT1 | B19: TOTAL TURNKEY RAN CAPEX PER SITE | C19: Combined BTS Hardware + Turnkey Rollout Services per Site | E19: site | G19: =G10+G18 | H19: =H10+H18 | I19: =I10+I18

Sheet Lot 2 - Power & Passive
A1: LOT 2: POWER SYSTEMS & PASSIVE INFRASTRUCTURE
A2: Official Bidding Bill of Quantities — Enter Quoted Unit Rates in Column G (USD)
A4: Item Code | B4: Equipment Description | C4: Technical Specification | D4: Application | E4: UoM | F4: Phase 1 Qty | G4: Unit Rate (USD) [Bidder Input] | H4: Unit Rate (PHP @ 55) | I4: Phase 1 Total (USD) | J4: Remarks / Bidder Model
A5: PWR-01 | B5: 12.0 kW Modular DC Rectifier Plant | C5: 19" 3U subrack, 4x 3.0 kW modules (N+1), SMPS controller, 96% eff | D5: Co-loc & Greenfield | E5: set | F5: 1000 | H5: =G5*55 | I5: =F5*G5
A6: PWR-02 | B6: 48V LiFePO4 Battery Bank | C6: Sized for >= 12.0 kWh usable energy over 4.0h @ 3.0 kW load, <=80% DoD, 80% SoH retention (minimum >= 20.0 kWh nominal installed bank capacity, min 400 Ah @ 48V, loss-based calculation) | D6: Co-loc & Greenfield | E6: set | F6: 1000 | H6: =G6*55 | I6: =F6*G6
A7: PWR-03 | B7: TowerCo DC Tap-Off Box & Submeter | C7: Enclosure, Class 1.0 revenue kWh meter, RS485 telemetry, SPD Type 2 | D7: Leased TowerCo Sites | E7: set | F7: 897 | H7: =G7*55 | I7: =F7*G7
A8: PWR-04 | B8: 15 kVA Soundproof Standby Genset | C8: Diesel, 230V 60Hz, 500L-1000L sub-base tank, ATS auto-transfer, <68dBA | D8: Greenfield Sites (Class T4) | E8: set | F8: 103 | H8: =G8*55 | I8: =F8*G8
A9: TOTAL-LOT2 | B9: TOTAL POWER SYSTEMS & ELECTRICAL INFRASTRUCTURE | C9: Total Phase 1 Capital Expenditure for Lot 2 Power Systems (Towers, compounds, and grounding are evaluated in Lot 5) | D9: 1,000 Sites Footprint | E9: lot | F9: 1000 | I9: =SUM(I5:I8) | J9: Evaluated Lot 2 Total

Sheet Lot 3 - 5G Core
A1: LOT 3: CLOUD-NATIVE 5G CORE NETWORK (5GC SA) & DATACENTER
A2: Official Bidding Bill of Quantities — Enter Quoted Prices in Column F and AMC % in Column G
A4: Item Code | B4: Core Subsystem | C4: Functional Description & Sizing | D4: Licensing / Delivery | E4: UoM | F4: Year 1 Price (USD) [Bidder Input] | G4: Annual AMC % [Bidder Input] | H4: Remarks / Bidder Model
A5: 5GC-HW-01 | B5: Compute Servers (2U Dual Socket) | C5: Dual Intel Xeon / AMD EPYC, 512GB RAM, redundant NVMe, dual 100GE NICs | D5: Hardware Purchase | E5: nodes
A6: 5GC-HW-02 | B6: High-Performance UPF Nodes | C6: 80 Gbps line-rate per node with DPDK/SR-IOV, N+1 redundancy across DCs | D6: Hardware Purchase | E6: nodes
A7: 5GC-HW-03 | B7: Datacenter Fabric & Security | C7: Spine/leaf 100G/25G switches, carrier next-gen firewalls, anti-DDoS | D7: Hardware Purchase | E7: lot
A8: 5GC-HW-04 | B8: Storage & Spares | C8: Enterprise NVMe redundant storage arrays, staging tooling, spares float | D8: Hardware Purchase | E8: lot
A9: 5GC-SW-01 | B9: 5GC Control Plane Software (1M Subs) | C9: AMF, SMF, PCF, UDM, UDR, AUSF, NRF, NSSF, CHF (1,000,000 registered subs) | D9: Perpetual License | E9: package
A10: 5GC-SW-02 | B10: Carrier-Grade NAT & DPI Software | C10: Deterministic CG-NAT port mapping + Layer-7 DPI bandwidth shaping | D10: Perpetual License | E10: package
A11: 5GC-SW-03 | B11: CaaS / Kubernetes Platform | C11: Enterprise CaaS container platform, service mesh, logging & telemetry | D11: Perpetual / Annual | E11: package
A12: 5GC-SVC-01 | B12: System Integration & RAN IOT | C12: High-level design, low-level design, RAN IOT, UAT and launch support | D12: Turnkey Services | E12: lot
A13: TOTAL-5GC | B13: TOTAL 5G CORE YEAR 1 CAPEX | C13: Dual Datacenter Active-Active Setup Dimensioned for 1,000,000 Subscribers | D13: Turnkey Initial | E13: system | F13: =SUM(F5:F12)

Sheet Lot 4 - OSS-BSS
A1: LOT 4: CONVERGED DIGITAL OSS/BSS & FIELD FORCE AUTOMATION
A2: Official Bidding Bill of Quantities — Enter Quoted Prices in Column F and AMC % in Column G
A4: Item Code | B4: OSS/BSS Functional Module | C4: Functional Scope & Volume Driver | D4: License Type | E4: UoM | F4: Year 1 Price (USD) [Bidder Input] | G4: Annual AMC % [Bidder Input] | H4: Remarks / Bidder Model
A5: BSS-01 | B5: Converged CRM & Product Catalog | C5: Omnichannel onboarding, self-care, 4 consumer tariffs + SME plans | D5: Perpetual Enterprise | E5: suite
A6: BSS-02 | B6: Real-Time Charging & Rating (CHF) | C6: CHF adapter, real-time balance tracking, zero-balance redirection | D6: Perpetual License | E6: suite
A7: BSS-03 | B7: Omnichannel Payment Gateway | C7: Direct API integrations: GCash, Maya, 7-Eleven CLiQQ, Bayad, QR Ph | D7: Integration Module | E7: module
A8: BSS-04 | B8: Billing & Invoicing Engine | C8: Postpaid billing for SME, enterprise anchor tenants, and dealer invoicing | D8: Perpetual License | E8: suite
A9: OSS-01 | B9: Field Force Management (FMS) | C9: Algorithmic automated dispatch handling 3,500 daily work orders | D9: Enterprise License | E9: suite
A10: OSS-02 | B10: Mobile Field Technician App | C10: Android app: GPS routing, barcode scan, live RF signal sweep tool | D10: Unlimited Users | E10: module
A11: OSS-03 | B11: CPE Warehouse Logistics & Reverse WMS | C11: Serialized asset tracking across depots, vehicle float, repossession | D11: Enterprise License | E11: suite
A12: OSS-04 | B12: Network Fault & Performance OSS | C12: Multi-vendor EMS integration, RCA correlation, synthetic SLA monitoring | D12: Enterprise License | E12: suite
A13: OSS-05 | B13: Regulatory Reporting & BI Engine | C13: NTC QoS reporting dashboards, churn analytics, spatial subscriber BI | D13: Enterprise License | E13: suite
A14: OSS-SVC | B14: Systems Integration, Testing & Launch | C14: End-to-end integration with Core, RAN, payment gateways and UAT launch | D14: Professional Services | E14: lot
A15: TOTAL-BSS | B15: TOTAL OSS/BSS YEAR 1 CAPEX | C15: Turnkey Digital Stack Dimensioned for 1,000,000 Initial Subscribers | D15: Turnkey Initial | E15: suite | F15: =SUM(F5:F14)

Sheet Lot 5 - Site Acq & Civils
A1: LOT 5: SITE ACQUISITION, DETAILED SITE SURVEY (TSSR), RF DESIGN & CIVIL WORKS
A2: Official Bidding Bill of Quantities — Enter Quoted Rates in Column F
A4: Item Code | B4: Service / Works Description | C4: Detailed Scope & Technical Specification | D4: Site Class Application | E4: UoM | F4: Phase 1 Qty | G4: Unit Rate (USD) [Bidder Input] | H4: Unit Rate (PHP @ 55) | I4: Phase 1 Total (USD) | J4: Remarks / Bidder Methodology
A5: CIV-SVC-01 | B5: Detailed Site Survey Report (TSSR) | C5: Tower structural load audit, 360-degree drone photo sweep, power/grounding audit, civil layout sketch, and PE endorsement. | D5: All Sites (Co-loc & Greenfield) | E5: site | F5: 1000 | H5: =G5*55 | I5: =F5*G5 | J5: Comprehensive TSSR
A6: CIV-SVC-02 | B6: Site Acquisition & Permitting Support | C6: LGU building permit processing, Barangay clearance, CAAP height clearance, and environmental compliance documentation. | D6: Greenfield Sites | E6: site | F6: 103 | H6: =G6*55 | I6: =F6*G6 | J6: Full permit clearance
A7: CIV-SVC-03 | B7: Equipment Pad Foundation & Cable Gantry | C7: Reinforced concrete plinth for outdoor DC power cabinet/battery, elevated cable tray/gantry, and AC interconnect point. | D7: Leased TowerCo Sites | E7: site | F7: 897 | H7: =G7*55 | I7: =F7*G7 | J7: Co-location upgrade
A8: CIV-SVC-04 | B8: Greenfield Compound Civil Works & Foundation | C8: 8m x 8m compound grading, perimeter chain-link security fence, crushed gravel bedding, and reinforced foundation slab. | D8: Greenfield Sites (Class T4) | E8: site | F8: 103 | H8: =G8*55 | I8: =F8*G8 | J8: Civil compound construction
A9: CIV-SVC-05 | B9: Grounding Grid & Lightning Protection System | C9: Exothermically welded copper ground ring (Cadweld), ground rods, copper busbar, and air terminal (<= 5.0 Ohms). | D9: Greenfield Sites (Class T4) | E9: site | F9: 103 | H9: =G9*55 | I9: =F9*G9 | J9: Dedicated earth ground ring
A10: CIV-SVC-06 | B10: 30m Galvanized Steel Monopole Tower | C10: ASTM A572 steel monopole, 250 km/h Category 5 wind rating, climbing ladder with fall arrest, rigging, erection, and certification. | D10: Greenfield Standard Height (Alternative A) | E10: site | F10: 80 | H10: =G10*55 | I10: =F10*G10 | J10: 80 sites standard (mutually exclusive with 40m)
A11: CIV-SVC-07 | B11: 40m Galvanized Steel Monopole Tower | C11: ASTM A572 steel monopole, 250 km/h Category 5 wind rating, fall arrest, rigging, erection, and structural PE certification. | D11: Greenfield High-Clearance (Alternative B) | E11: site | F11: 23 | H11: =G11*55 | I11: =F11*G11 | J11: 23 sites terrain/canopy (mutually exclusive with 30m)
A12: CIV-SVC-08 | B12: RF Propagation Modeling & Siting Optimization | C12: High-resolution 3D ray-tracing simulation, local clutter calibration, candidate search ring generation, and nominal design. | D12: Macro Network Footprint | E12: site | F12: 1000 | H12: =G12*55 | I12: =F12*G12 | J12: RF planning & candidate search rings
A13: CIV-SVC-09 | B13: Cluster RF Optimization & Drive Testing Services | C13: Multi-site cluster drive testing, antenna tilt/azimuth physical optimization, pilot pollution removal, and handover tuning. | D13: Multi-Site Clusters (per site share) | E13: site | F13: 1000 | H13: =G13*55 | I13: =F13*G13 | J13: Cluster drive testing & tuning
A14: TOTAL-LOT5 | B14: TOTAL PHASE 1 CIVIL & SITING WORKS (USD) | C14: Evaluated Turnkey Site Acquisition, Survey, Towers & Civil Infrastructure | D14: 1,000 Sites Footprint (897 Co-loc + 103 Greenfield) | E14: lot | F14: 1000 | G14: =SUM(G5:G13) | H14: Evaluated Rate | I14: =SUM(I5:I13) | J14: Evaluated Phase 1 Total

Sheet Lot 6 - Managed Services
A1: LOT 6: NATIONWIDE MANAGED SERVICES & 24/7 NETWORK OPERATIONS
A2: Official Bidding Bill of Quantities — Enter Quoted Monthly Rate per Site in Column E
A4: Item Code | B4: Service Domain | C4: Operational Scope of Work | D4: SLA Target | E4: Monthly Rate / Site (PHP) [Bidder Input] | F4: Monthly Rate (USD @ 55) | G4: Annual Cost / Site (USD) | H4: Remarks
A5: MS-01 | B5: 24/7 Tier-2/Tier-3 Central NOC | C5: Continuous 24/7/365 active monitoring, alarm triage, dispatch | D5: 99.95% Target (99.70% Min SLA) | F5: =E5/55 | G5: =F5*12
A6: MS-02 | B6: First Line Maintenance (FLM) | C6: Nationwide 24/7 emergency restoration, 4x4 response vehicles | D6: MTTR <=2h (U) / <=4h (R) | F6: =E6/55 | G6: =F6*12
A7: MS-03 | B7: Preventive Maintenance (PM) | C7: Quarterly site inspections: power, RF jumpers, batteries, grounding | D7: 100% Quarterly Audit | F7: =E7/55 | G7: =F7*12
A8: MS-04 | B8: Spare Parts Logistics & Warehousing | C8: SPMS regional buffer float, next-business-day (NBD) replacement | D8: NBD Delivery SLA | F8: =E8/55 | G8: =F8*12
A9: MS-05 | B9: Continuous RF Cluster Optimization | C9: Routine KPI analysis, neighbor list optimization, interference tuning | D9: Zero degraded clusters | F9: =E9/55 | G9: =F9*12
A10: TOTAL-MS | B10: TOTAL MANAGED SERVICES PER SITE | C10: Full-Scope Active Network Telecom O&M Managed Operations | D10: Strict SLA Governed | E10: =SUM(E5:E9) | F10: =SUM(F5:F9) | G10: =SUM(G5:G9)

Sheet Lot 7 - 5G CPE
A1: LOT 7: 5G HIGH-GAIN CUSTOMER PREMISES EQUIPMENT (CPE)
A2: Official Bidding Bill of Quantities — Enter Quoted Unit Rate in Column F
A4: Item Code | B4: CPE Terminal Model | C4: Technical Specifications | D4: Target Order Qty (P1) | E4: UoM | F4: Unit Rate (USD) [Bidder Input] | G4: Total Phase 1 Cost (USD) | H4: Remarks / Bidder Model
A5: CPE-01 | B5: Indoor 5G High-Gain FWA Router | C5: Band n50 native, >=8.0 dBi internal antenna, Wi-Fi 6 AX1800/AX3000, 1x 2.5GE + 2x 1GE ports, TR-069/TR-369 | D5: 350000 | E5: units | G5: =D5*F5
A6: CPE-02 | B6: Outdoor 5G High-Gain FWA Terminal Package | C6: Band n50, IP67 enclosure, >=12.0 dBi directional antenna, 1x 2.5GE PoE, bundled indoor Wi-Fi 6 router & PoE injector | D6: 15000 | E6: units | G6: =D6*F6
A7: CPE-SVC | B7: Device Staging, Pre-Configuration & SIM Locking | C7: Firmware customization, operator APN & SIM locking, custom retail packaging for all Phase 1 terminals | D7: 365000 | E7: units | G7: =D7*F7
A8: TOTAL-LOT7 | B8: TOTAL 5G CUSTOMER PREMISES EQUIPMENT (CPE) | C8: Total Initial Terminal Supply & Staging (365,000 Total Devices) | D8: 365000 | E8: units | G8: =SUM(G5:G7) | H8: Evaluated Lot 7 Total

Sheet Form C - 10-Year TCO Schedule
A1: Telecommunications Technology Solutions Incorporated (TelTech)
A2: Form C: Phase 1 (1,000 Sites) 10-Year Baseline Lifecycle Total Cost of Ownership (TCO)
A3: Tender Ref: RFP-TELTECH-FWA-2026-001 | Baseline Evaluation: Committed 1,000 Sites (Lots 1, 2, 5 Turnkey) | Expansion Yrs 2-5 Call-Off
A5: Cost Category / Lifecycle Element | B5: Phase 1 Capex (Yr 1) | C5: Yr 2 | D5: Yr 3 | E5: Yr 4 | F5: Yr 5 | G5: Yrs 6-10 Cumulative | H5: 10-Year Total TCO (USD) | I5: Notes & Pricing Assumptions
A6: 1. 5G RAN Network Capex (Lots 1, 2, 5) | B6: ='Lot 1 - RAN & Rollout'!H19+'Lot 2 - Power & Passive'!I9+'Lot 5 - Site Acq & Civils'!I14 | C6: 0 | D6: 0 | E6: 0 | F6: 0 | G6: 0 | H6: =SUM(B6:G6) | I6: [Evaluated Tender Input] Initial 1,000 sites turnkey rollout (Lots 1, 2, 5 Phase 1 Totals). Expansion Yrs 2-5 Capex evaluated via contractual call-off rate card.
A7: 2. 5G Core Network & Cloud Infrastructure (Lot 3) | B7: ='Lot 3 - 5G Core'!F13 | C7: 0 | D7: 0 | E7: 0 | F7: 0 | G7: 0 | H7: =SUM(B7:G7) | I7: [Evaluated Tender Input] Day-1 Core & DC infrastructure dimensioned for 1.0M subscribers (perpetual license + compute fabric).
A8: 3. Digital OSS/BSS & Automation (Lot 4) | B8: ='Lot 4 - OSS-BSS'!F15 | C8: 0 | D8: 0 | E8: 0 | F8: 0 | G8: 0 | H8: =SUM(B8:G8) | I8: [Evaluated Tender Input] Turnkey BSS/OSS stack, CRM, prepaid billing, and FMS dispatch engine.
A9: 4. 5G CPE Terminals Supply (Lot 7) | B9: ='Lot 7 - 5G CPE'!G8 | C9: 0 | D9: 0 | E9: 0 | F9: 0 | G9: 0 | H9: =SUM(B9:G9) | I9: [Evaluated Tender Input] Phase 1 initial supply of 365,000 subscriber terminals (350k indoor + 15k outdoor).
A10: 5. Annual Software Support & AMC (5GC + OSS/BSS) | B10: 0 | C10: =('Lot 3 - 5G Core'!F13*0.10)+('Lot 4 - OSS-BSS'!F15*0.10) | D10: =('Lot 3 - 5G Core'!F13*0.10)+('Lot 4 - OSS-BSS'!F15*0.10) | E10: =('Lot 3 - 5G Core'!F13*0.10)+('Lot 4 - OSS-BSS'!F15*0.10) | F10: =('Lot 3 - 5G Core'!F13*0.10)+('Lot 4 - OSS-BSS'!F15*0.10) | G10: =(('Lot 3 - 5G Core'!F13*0.10)+('Lot 4 - OSS-BSS'!F15*0.10))*5 | H10: =SUM(B10:G10) | I10: [Prescribed Evaluated Parameter] 10.0% p.a. of Core (Lot 3) + OSS/BSS (Lot 4) software Capex starting Yr 2 following 12-month Day-1 warranty.
A11: 6. Managed Services & Field Operations (Lot 6) | B11: ='Lot 6 - Managed Services'!G10*1000 | C11: ='Lot 6 - Managed Services'!G10*1000 | D11: ='Lot 6 - Managed Services'!G10*1000 | E11: ='Lot 6 - Managed Services'!G10*1000 | F11: ='Lot 6 - Managed Services'!G10*1000 | G11: ='Lot 6 - Managed Services'!G10*1000*5 | H11: =SUM(B11:G11) | I11: [Prescribed Evaluated Parameter] Evaluated on Phase 1 network baseline (1,000 sites footprint @ Lot 6 quoted annual rate). Scales proportionately upon expansion call-off.
A12: 7. Spare Parts Float & RMA Replenishment | B12: =B6*0.02 | C12: =B6*0.01 | D12: =B6*0.01 | E12: =B6*0.01 | F12: =B6*0.01 | G12: =B6*0.05 | H12: =SUM(B12:G12) | I12: [Prescribed Evaluated Parameter] 2.0% initial spares float in Yr 1, 1.0% annual replenishment in Yrs 2-5, and 5.0% cumulative in Yrs 6-10.
A13: TOTAL EVALUATED 10-YEAR TCO (USD) — Phase 1 Network Baseline | B13: =SUM(B6:B12) | C13: =SUM(C6:C12) | D13: =SUM(D6:D12) | E13: =SUM(E6:E12) | F13: =SUM(F6:F12) | G13: =SUM(G6:G12) | H13: =SUM(H6:H12) | I13: Evaluated Total Lifecycle Cost of Ownership for Phase 1 Baseline
A15: Note: This schedule establishes the official evaluated 10-Year Lifecycle TCO for the committed Phase 1 network baseline (1,000 macro BTS sites). Expansion Capex for Years 2 to 5 (Phases 2 to 5, 1,000 sites/year up to 5,000 sites total) is governed by the firm unit rates in Lots 1, 2, 5, and 7 under contractual call-off options (Section 4.5).

Sheet Form D - Vendor Financing
A1: FORM D: MANDATORY VENDOR FINANCING PROPOSAL
A2: Official Bidding Terms — Enter Proposed Binding Financing Terms in Column D
A4: Parameter Ref | B4: Financing Term / Condition | C4: Operator Mandatory Requirement | D4: Bidder Binding Offer [Bidder Input] | E4: Compliance / Notes
A5: FIN-01 | B5: Financing Structure | C5: OEM Vendor Financing, Buyer's Credit, or ECA-backed facility
A6: FIN-02 | B6: Financing Quantum (% of Capex) | C6: Minimum 80.0% of total eligible Capex (Lots 1, 3, Turnkey Services)
A7: FIN-03 | B7: Equity Downpayment (% of Capex) | C7: Maximum 20.0% downpayment upon contract signing
A8: FIN-04 | B8: Total Facility Tenor | C8: Flexible facility tenor up to 20 Years (minimum 4 Years, 5+ Years Preferred)
A9: FIN-05 | B9: Principal Grace Period | C9: Deferred payment / principal grace period up to 10 Years (minimum 12 Months, 18+ Months Preferred)
A10: FIN-06 | B10: Indicative Annual Interest Rate | C10: Fixed commercial rate (preferred <= 6.50% p.a.) or competitive benchmark to SOFR + spread
A11: FIN-07 | B11: Repayment Schedule | C11: Equal quarterly or semi-annual principal & interest amortizations
A12: FIN-08 | B12: Collateral / Asset Pledge | C12: Pledge on acquired telecom hardware without restrictive corporate liens
A13: FIN-09 | B13: Credit Committee Status | C13: Board or Credit Committee approved term sheet attached with bid
